txl_local_terminals/__init__.py
txl_local_terminals/main.py
txl_local_terminals/terminal.py
txl_local_terminals/win_terminal.py
txl_local_terminals-0.3.8.dist-info/METADATA
txl_local_terminals-0.3.8.dist-info/WHEEL
txl_local_terminals-0.3.8.dist-info/entry_points.txt
txl_local_terminals-0.3.8.dist-info/licenses/LICENSE.txt
txl_local_terminals-0.3.8.dist-info/RECORD
