Metadata-Version: 2.4
Name: txl_local_terminals
Version: 0.3.8
Summary: TXL plugin for local terminals
Project-URL: Source, https://github.com/davidbrochart/jpterm/tree/main/plugins/local_terminals
Author-email: David Brochart <david.brochart@gmail.com>
License-Expression: MIT
License-File: LICENSE.txt
Classifier: Development Status :: 4 - Beta
Classifier: Programming Language :: Python
Classifier: Programming Language :: Python :: 3.10
Classifier: Programming Language :: Python :: 3.11
Classifier: Programming Language :: Python :: 3.12
Classifier: Programming Language :: Python :: 3.13
Classifier: Programming Language :: Python :: Implementation :: CPython
Classifier: Programming Language :: Python :: Implementation :: PyPy
Requires-Python: >=3.10
Requires-Dist: anyio<5,>=3.7.0
Requires-Dist: pywinpty; platform_system == 'Windows'
Requires-Dist: txl==0.3.3
